RestfulApi/__init__.py
RestfulApi/ComusApi/__init__.py
RestfulApi/ComusApi/manage.py
RestfulApi/ComusApi/ComusApi/__init__.py
RestfulApi/ComusApi/ComusApi/asgi.py
RestfulApi/ComusApi/ComusApi/settings.py
RestfulApi/ComusApi/ComusApi/urls.py
RestfulApi/ComusApi/ComusApi/wsgi.py
RestfulApi/ComusApi/ComusDis/__init__.py
RestfulApi/ComusApi/ComusDis/admin.py
RestfulApi/ComusApi/ComusDis/apps.py
RestfulApi/ComusApi/ComusDis/models.py
RestfulApi/ComusApi/ComusDis/serializers.py
RestfulApi/ComusApi/ComusDis/tests.py
RestfulApi/ComusApi/ComusDis/urls.py
RestfulApi/ComusApi/ComusDis/views.py
RestfulApi/ComusApi/ComusDis/migrations/0001_initial.py
RestfulApi/ComusApi/ComusDis/migrations/0002_alter_comusctrlparsmodel_comus_dis_uuid.py
RestfulApi/ComusApi/ComusDis/migrations/0003_comusoutparsmodel.py
RestfulApi/ComusApi/ComusDis/migrations/__init__.py
pycomus/__init__.py
pycomus/ComusDis/CmsDis.py
pycomus/ComusDis/CmsGridPars.py
pycomus/ComusDis/CmsMd.py
pycomus/ComusDis/CmsOutPars.py
pycomus/ComusDis/CmsPars.py
pycomus/ComusDis/CmsTime.py
pycomus/ComusDis/GridCell.py
pycomus/ComusDis/GridLyr.py
pycomus/ComusDis/__init__.py
pycomus/Package/CDRN.py
pycomus/Package/CEVT.py
pycomus/Package/CGHB.py
pycomus/Package/CHFB.py
pycomus/Package/CIBS.py
pycomus/Package/CLAK.py
pycomus/Package/CRCH.py
pycomus/Package/CREG.py
pycomus/Package/CRES.py
pycomus/Package/CRIV.py
pycomus/Package/CSHB.py
pycomus/Package/CSTR.py
pycomus/Package/CSUB.py
pycomus/Package/CWEL.py
pycomus/Package/__init__.py
pycomus/Utils/BoundaryCheck.py
pycomus/Utils/CONSTANTS.py
pycomus/Utils/LinuxCheckParams.so
pycomus/Utils/LinuxComus.so
pycomus/Utils/Map.py
pycomus/Utils/ReadData.py
pycomus/Utils/WinCheckParams.dll
pycomus/Utils/WinComus.dll
pycomus/Utils/__init__.py
PyCOMUS-1.3.dist-info/METADATA
PyCOMUS-1.3.dist-info/WHEEL
PyCOMUS-1.3.dist-info/top_level.txt
PyCOMUS-1.3.dist-info/RECORD
