Metadata-Version: 2.1
Name: PyCOMUS
Version: 1.3
Summary: A Python library for invoking the COMUS model for groundwater numerical simulation.
Home-page: https://github.com/ZhenjiangWuHydro/PyCOMUS
Author: Zhenjiang Wu
Author-email: zhenjiangwu613@gmail.com
Classifier: Programming Language :: Python :: 3
Classifier: License :: OSI Approved :: MIT License
Classifier: Operating System :: OS Independent
Requires-Python: >=3.6
